stylomepy/Silabizator.py
stylomepy/StyleMetrics.py
stylomepy/TextStatistics.py
stylomepy/VocabularyRichness.py
stylomepy/__init__.py
stylomepy/coherenceMetrics.py
stylomepy/englishRIAlgorithms.py
stylomepy/formality.py
stylomepy/spanishRIAlgorithms.py
stylomepy/styleTokenizer.py
stylomepy-0.31.data/data/LICENSE.txt
stylomepy-0.31.data/data/requirements.txt
stylomepy-0.31.dist-info/LICENSE.txt
stylomepy-0.31.dist-info/METADATA
stylomepy-0.31.dist-info/WHEEL
stylomepy-0.31.dist-info/top_level.txt
stylomepy-0.31.dist-info/RECORD
